README.txt
setup.py
Flowgiston.egg-info/PKG-INFO
Flowgiston.egg-info/SOURCES.txt
Flowgiston.egg-info/dependency_links.txt
Flowgiston.egg-info/requires.txt
Flowgiston.egg-info/top_level.txt
flowgiston/__init__.py
flowgiston/base.py
test/test_flowchart.py