Metadata-Version: 1.2
Name: Flowgiston
Version: 0.1
Summary: UNKNOWN
Home-page: UNKNOWN
Author: Matthew P. Gordon
Author-email: matt@kairosaerospace.com
Maintainer: Matthew P. Gordon
Maintainer-email: matt@kairosaerospace.com
License: LICENSE.txt
Platform: UNKNOWN
